tie_decay_epidemics/TieDecay.py
tie_decay_epidemics/__init__.py
tie_decay_epidemics/example.py
tie_decay_epidemics/tie_decay_epidemics.py
tie_decay_epidemics/utils.py
tie_decay_epidemics-0.0.2.dist-info/LICENSE
tie_decay_epidemics-0.0.2.dist-info/METADATA
tie_decay_epidemics-0.0.2.dist-info/WHEEL
tie_decay_epidemics-0.0.2.dist-info/top_level.txt
tie_decay_epidemics-0.0.2.dist-info/RECORD
