Metadata-Version: 2.1
Name: tie-decay-epidemics
Version: 0.0.2
Summary: Tie-Decay Epidemics contains the scripts that allow you to simulate epidemic spreading on a tie-decay network.
Home-page: https://github.com/qinyichen/tie-decay-epidemics
Author: Qinyi Chen
Author-email: qinyichen@ucla.edu
License: MIT
Keywords: tie_decay_epidemics
Platform: UNKNOWN
Classifier: Development Status :: 2 - Pre-Alpha
Classifier: Intended Audience :: Science/Research 
Classifier: License :: OSI Approved :: MIT License
Classifier: Natural Language :: English
Classifier: Programming Language :: Python
Classifier: Programming Language :: Python :: 3
Classifier: Programming Language :: Python :: 3 :: Only
Classifier: Programming Language :: Python :: 3.6
Classifier: Programming Language :: Python :: 3.7
Classifier: Programming Language :: Python :: 3.8
Classifier: Topic :: Scientific/Engineering
Requires-Python: >=3.6
Requires-Dist: numpy
Requires-Dist: scipy
Requires-Dist: pandas
Requires-Dist: matplotlib
Provides-Extra: all
Requires-Dist: numpy ; extra == 'all'
Requires-Dist: scipy ; extra == 'all'
Requires-Dist: pandas ; extra == 'all'
Requires-Dist: matplotlib ; extra == 'all'
Requires-Dist: bump2version (>=1.0.0) ; extra == 'all'
Requires-Dist: ipython (>=7.5.0) ; extra == 'all'
Requires-Dist: twine (>=1.13.0) ; extra == 'all'
Requires-Dist: wheel (>=0.33.1) ; extra == 'all'
Provides-Extra: dev
Requires-Dist: bump2version (>=1.0.0) ; extra == 'dev'
Requires-Dist: ipython (>=7.5.0) ; extra == 'dev'
Requires-Dist: twine (>=1.13.0) ; extra == 'dev'
Requires-Dist: wheel (>=0.33.1) ; extra == 'dev'
Provides-Extra: docs
Provides-Extra: setup
Provides-Extra: test
